{
	"format_version": "1.12.0",
	"minecraft:geometry": [
		{
			"description": {
				"identifier": "geometry.weapon.double_dagger",
				"texture_width": 16,
				"texture_height": 16,
				"visible_bounds_width": 3,
				"visible_bounds_height": 1.5,
				"visible_bounds_offset": [0, 0.25, 0]
			},
			"bones": [
				{
					"name": "leftItem",
					"pivot": [2.5, 0.5, 3.5]
				},
				{
					"name": "leftDagger",
					"parent": "leftItem",
					"pivot": [2.5, 0.5, 1.25],
					"rotation": [0, 180, 0],
					"cubes": [
						{
							"origin": [2.2, 0, -3.5],
							"size": [0.7, 1, 5],
							"uv": {
								"north": {"uv": [9, 3], "uv_size": [0.5, 1]},
								"east": {"uv": [0, 5], "uv_size": [4, 1]},
								"south": {"uv": [9, 4], "uv_size": [0.5, 1]},
								"west": {"uv": [4, 5], "uv_size": [4, 1]},
								"up": {"uv": [5, 6], "uv_size": [0.5, 4]},
								"down": {"uv": [6, 10], "uv_size": [0.5, -4]}
							}
						},
						{
							"origin": [2.4, 0, 1.5],
							"size": [0.25, 1, 6],
							"uv": {
								"north": {"uv": [9, 5], "uv_size": [0.5, 1]},
								"east": {"uv": [0, 2], "uv_size": [6, 1]},
								"south": {"uv": [9, 6], "uv_size": [0.5, 1]},
								"west": {"uv": [0, 3], "uv_size": [6, 1]},
								"up": {"uv": [2, 6], "uv_size": [0.5, 6]},
								"down": {"uv": [3, 12], "uv_size": [0.5, -6]}
							}
						},
						{
							"origin": [2.4, 0.14142, 7.07746],
							"size": [0.25, 0.70711, 0.70711],
							"pivot": [2.5, 0.41421, 7.47157],
							"rotation": [-45, 0, 0],
							"uv": {
								"north": {"uv": [10, 10], "uv_size": [0.5, 0.5]},
								"east": {"uv": [11, 0], "uv_size": [0.5, 0.5]},
								"south": {"uv": [11, 1], "uv_size": [0.5, 0.5]},
								"west": {"uv": [11, 2], "uv_size": [0.5, 0.5]},
								"up": {"uv": [11, 3], "uv_size": [0.5, 0.5]},
								"down": {"uv": [4, 11.5], "uv_size": [0.5, -0.5]}
							}
						},
						{
							"origin": [2.2, -0.5, 1.35],
							"size": [0.7, 2, 0.25],
							"uv": {
								"north": {"uv": [8, 2], "uv_size": [0.5, 2]},
								"east": {"uv": [8, 4], "uv_size": [0.5, 2]},
								"south": {"uv": [8, 6], "uv_size": [0.5, 2]},
								"west": {"uv": [7, 8], "uv_size": [0.5, 2]},
								"up": {"uv": [11, 4], "uv_size": [0.5, 0.5]},
								"down": {"uv": [5, 11.5], "uv_size": [0.5, -0.5]}
							}
						},
						{
							"origin": [2.20294, 1.91716, 1.35],
							"size": [0.49497, 0.49497, 0.25],
							"pivot": [1.69792, 1.71213, 2.35],
							"rotation": [0, 0, 45],
							"uv": {
								"north": {"uv": [11, 5], "uv_size": [0.5, 0.5]},
								"east": {"uv": [6, 11], "uv_size": [0.5, 0.5]},
								"south": {"uv": [11, 6], "uv_size": [0.5, 0.5]},
								"west": {"uv": [7, 11], "uv_size": [0.5, 0.5]},
								"up": {"uv": [11, 7], "uv_size": [0.5, 0.5]},
								"down": {"uv": [8, 11.5], "uv_size": [0.5, -0.5]}
							}
						},
						{
							"origin": [2.20294, -0.08284, 1.35],
							"size": [0.49497, 0.49497, 0.25],
							"pivot": [1.69792, -0.28787, 2.35],
							"rotation": [0, 0, 45],
							"uv": {
								"north": {"uv": [11, 8], "uv_size": [0.5, 0.5]},
								"east": {"uv": [9, 11], "uv_size": [0.5, 0.5]},
								"south": {"uv": [11, 9], "uv_size": [0.5, 0.5]},
								"west": {"uv": [10, 11], "uv_size": [0.5, 0.5]},
								"up": {"uv": [11, 10], "uv_size": [0.5, 0.5]},
								"down": {"uv": [11, 11.5], "uv_size": [0.5, -0.5]}
							}
						}
					]
				},
				{
					"name": "rightItem",
					"pivot": [-2.5, 0.5, -3]
				},
				{
					"name": "rightDagger",
					"parent": "rightItem",
					"pivot": [-2.5, 0.5, -3],
					"cubes": [
						{
							"origin": [-2.8, 0, -6],
							"size": [0.7, 1, 5],
							"uv": {
								"north": {"uv": [8, 8], "uv_size": [0.5, 1]},
								"east": {"uv": [0, 4], "uv_size": [4, 1]},
								"south": {"uv": [9, 0], "uv_size": [0.5, 1]},
								"west": {"uv": [4, 4], "uv_size": [4, 1]},
								"up": {"uv": [6, 0], "uv_size": [0.5, 4]},
								"down": {"uv": [4, 10], "uv_size": [0.5, -4]}
							}
						},
						{
							"origin": [-2.6, 0, -1],
							"size": [0.25, 1, 6],
							"uv": {
								"north": {"uv": [9, 1], "uv_size": [0.5, 1]},
								"east": {"uv": [0, 0], "uv_size": [6, 1]},
								"south": {"uv": [9, 2], "uv_size": [0.5, 1]},
								"west": {"uv": [0, 1], "uv_size": [6, 1]},
								"up": {"uv": [0, 6], "uv_size": [0.5, 6]},
								"down": {"uv": [1, 12], "uv_size": [0.5, -6]}
							}
						},
						{
							"origin": [-2.6, 0.14142, 4.57746],
							"size": [0.25, 0.70711, 0.70711],
							"pivot": [-2.5, 0.41421, 4.97157],
							"rotation": [-45, 0, 0],
							"uv": {
								"north": {"uv": [9, 7], "uv_size": [0.5, 0.5]},
								"east": {"uv": [8, 9], "uv_size": [0.5, 0.5]},
								"south": {"uv": [9, 8], "uv_size": [0.5, 0.5]},
								"west": {"uv": [9, 9], "uv_size": [0.5, 0.5]},
								"up": {"uv": [10, 0], "uv_size": [0.5, 0.5]},
								"down": {"uv": [10, 1.5], "uv_size": [0.5, -0.5]}
							}
						},
						{
							"origin": [-2.8, -0.5, -1.15],
							"size": [0.7, 2, 0.25],
							"uv": {
								"north": {"uv": [7, 0], "uv_size": [0.5, 2]},
								"east": {"uv": [7, 2], "uv_size": [0.5, 2]},
								"south": {"uv": [7, 6], "uv_size": [0.5, 2]},
								"west": {"uv": [8, 0], "uv_size": [0.5, 2]},
								"up": {"uv": [10, 2], "uv_size": [0.5, 0.5]},
								"down": {"uv": [10, 3.5], "uv_size": [0.5, -0.5]}
							}
						},
						{
							"origin": [-2.79706, 1.91716, -1.15],
							"size": [0.49497, 0.49497, 0.25],
							"pivot": [-3.30208, 1.71213, -0.15],
							"rotation": [0, 0, 45],
							"uv": {
								"north": {"uv": [4, 10], "uv_size": [0.5, 0.5]},
								"east": {"uv": [10, 4], "uv_size": [0.5, 0.5]},
								"south": {"uv": [5, 10], "uv_size": [0.5, 0.5]},
								"west": {"uv": [10, 5], "uv_size": [0.5, 0.5]},
								"up": {"uv": [6, 10], "uv_size": [0.5, 0.5]},
								"down": {"uv": [10, 6.5], "uv_size": [0.5, -0.5]}
							}
						},
						{
							"origin": [-2.79706, -0.08284, -1.15],
							"size": [0.49497, 0.49497, 0.25],
							"pivot": [-3.30208, -0.28787, -0.15],
							"rotation": [0, 0, 45],
							"uv": {
								"north": {"uv": [7, 10], "uv_size": [0.5, 0.5]},
								"east": {"uv": [10, 7], "uv_size": [0.5, 0.5]},
								"south": {"uv": [8, 10], "uv_size": [0.5, 0.5]},
								"west": {"uv": [10, 8], "uv_size": [0.5, 0.5]},
								"up": {"uv": [9, 10], "uv_size": [0.5, 0.5]},
								"down": {"uv": [10, 9.5], "uv_size": [0.5, -0.5]}
							}
						}
					]
				}
			]
		}
	]
}